{
  "_comment": "Conversio demo: start zoomed out (mark LOD) so the directional pointer marks are visible, select the Spearmen, press V, and watch the pointer marks rotate 180° in place. The camera zooms in mid-maneuver to show the figure-LOD squash animation as each soldier silhouette goes edge-on during the turn.",
  "seed": "12345",
  "camera": [
    {"tick": 0,   "x": 500.0, "y": 300.0, "zoom": 0.8},
    {"tick": 60,  "x": 500.0, "y": 270.0, "zoom": 1.8}
  ],
  "steps": [
    {"tick": 10, "click": [500, 300]},
    {"tick": 30, "key": "V"}
  ]
}
